{
  "accuracy": 2.9,
  "area": "Australia - Queensland, South Australia, Western Australia, federal areas offshore west of 129°E.",
  "authority": "EPSG",
  "bbox": [
    -9.37,
    109.23,
    -38.53,
    153.61
  ],
  "code": "62036405",
  "default_trans": 15785,
  "kind": "CRS-GEOGCRS",
  "name": "AGD84 (deg)",
  "proj4": "",
  "trans": [
    1109,
    1236,
    1279,
    1280,
    1559,
    1593,
    1669,
    1804,
    8192,
    8194,
    8560,
    8579,
    15785,
    15789
  ],
  "unit": "degree",
  "wkt": ""
}